LICENSE.md
README.md
setup.cfg
setup.py
tests/__init__.py
tests/loading_units_test.py
tests/multigroup_test.py
tests/time_test.py
unitates.egg-info/PKG-INFO
unitates.egg-info/SOURCES.txt
unitates.egg-info/dependency_links.txt
unitates.egg-info/top_level.txt
units/__init__.py
units/constants/__init__.py
units/constants/length.py
units/constants/time.py