Metadata-Version: 2.1
Name: unitates
Version: 1.0.13
Summary: Python library for working with custom and predefined number measurement units
Home-page: UNKNOWN
Author: liubomyr.ivanitskyi
Author-email: lubomyr.ivanitskiy@gmail.com
License: MIT License
Platform: UNKNOWN
License-File: LICENSE.md
